secretm/.gitignore
secretm/__init__.py
secretm/secretm.py
secretm/secrets.enc
secretm-0.1.0.dist-info/LICENSE
secretm-0.1.0.dist-info/WHEEL
secretm-0.1.0.dist-info/METADATA
secretm-0.1.0.dist-info/RECORD
