Metadata-Version: 2.1
Name: secretm
Version: 0.1.0
Summary: 
Author: baileywickham
Author-email: baileywickham@gmail.com
Requires-Python: >=3.8,<4.0
Classifier: Programming Language :: Python :: 3
Classifier: Programming Language :: Python :: 3.10
Classifier: Programming Language :: Python :: 3.8
Classifier: Programming Language :: Python :: 3.9
Requires-Dist: PyYAML (>=6.0,<7.0)
Requires-Dist: pycryptodome (>=3.11.0,<4.0.0)
